e3/py.typed
e3/testsuite/__init__.py
e3/testsuite/_helpers.py
e3/testsuite/control.py
e3/testsuite/event_notifications.py
e3/testsuite/find_skipped_tests.py
e3/testsuite/fragment.py
e3/testsuite/main.py
e3/testsuite/multiprocess_scheduler.py
e3/testsuite/optfileparser.py
e3/testsuite/result.py
e3/testsuite/running_status.py
e3/testsuite/testcase_finder.py
e3/testsuite/utils.py
e3/testsuite/driver/__init__.py
e3/testsuite/driver/adacore.py
e3/testsuite/driver/classic.py
e3/testsuite/driver/diff.py
e3/testsuite/report/__init__.py
e3/testsuite/report/display.py
e3/testsuite/report/gaia.py
e3/testsuite/report/index.py
e3/testsuite/report/rewriting.py
e3/testsuite/report/xunit.py
e3_testsuite-27.3.dist-info/licenses/LICENSE
e3_testsuite-27.3.dist-info/METADATA
e3_testsuite-27.3.dist-info/WHEEL
e3_testsuite-27.3.dist-info/entry_points.txt
e3_testsuite-27.3.dist-info/top_level.txt
e3_testsuite-27.3.dist-info/RECORD
