Metadata-Version: 2.4
Name: e3-testsuite
Version: 27.3
Summary: E3 testsuite
Author: AdaCore's IT Team
License: GPLv3
Classifier: Development Status :: 3 - Alpha
Classifier: Intended Audience :: Developers
Classifier: License :: OSI Approved :: GNU General Public License v3 (GPLv3)
Classifier: Programming Language :: Python :: 3.9
Classifier: Programming Language :: Python :: 3.10
Classifier: Programming Language :: Python :: 3.11
Classifier: Topic :: Software Development :: Build Tools
License-File: LICENSE
Requires-Dist: e3-core
Dynamic: license-file
